promptcompose/__init__.py
promptcompose/prompt_compose.py
promptcompose/py.typed
promptcompose/constants/__init__.py
promptcompose/constants/endpoints.py
promptcompose/constants/messages.py
promptcompose/core/__init__.py
promptcompose/core/http_client.py
promptcompose/errors/__init__.py
promptcompose/errors/api_error.py
promptcompose/errors/sdk_error.py
promptcompose/errors/validation_error.py
promptcompose/types/__init__.py
promptcompose/types/ab_test.py
promptcompose/types/prompt.py
promptcompose/utils/__init__.py
promptcompose/utils/interpolate_prompt.py
promptcompose/utils/logger.py
promptcompose/utils/validate.py
promptcompose-0.1.1.dist-info/licenses/LICENSE
promptcompose-0.1.1.dist-info/METADATA
promptcompose-0.1.1.dist-info/WHEEL
promptcompose-0.1.1.dist-info/top_level.txt
promptcompose-0.1.1.dist-info/RECORD
