Metadata-Version: 2.4
Name: promptcompose
Version: 0.1.1
Summary: SDK for integrating with PromptCompose API to resolve and manage AI prompts.
Author-email: PromptCompose <admin@promptcompose.ai>
License: MIT
Project-URL: Homepage, https://github.com/promptcompose/python-sdk
Project-URL: Repository, https://github.com/promptcompose/python-sdk
Project-URL: Issues, https://github.com/promptcompose/python-sdk/issues
Keywords: sdk,ai,prompt,ab-testing,python,llm
Classifier: Development Status :: 4 - Beta
Classifier: Intended Audience :: Developers
Classifier: License :: OSI Approved :: MIT License
Classifier: Programming Language :: Python :: 3
Classifier: Programming Language :: Python :: 3.8
Classifier: Programming Language :: Python :: 3.9
Classifier: Programming Language :: Python :: 3.10
Classifier: Programming Language :: Python :: 3.11
Classifier: Programming Language :: Python :: 3.12
Requires-Python: >=3.8
License-File: LICENSE
Requires-Dist: requests>=2.25.0
Requires-Dist: typing-extensions>=4.0.0
Dynamic: license-file
